gpssi/__init__.py
gpssi/covariance.py
gpssi/gpssi.py
gpssi/kernel.py
gpssi/misc.py
gpssi-0.1.2.dist-info/LICENSE
gpssi-0.1.2.dist-info/METADATA
gpssi-0.1.2.dist-info/WHEEL
gpssi-0.1.2.dist-info/top_level.txt
gpssi-0.1.2.dist-info/RECORD
