Metadata-Version: 2.1
Name: gpssi
Version: 0.1.2
Summary: Sampling image segmentations with Gaussian process
Home-page: https://github.com/alainjungo/gpssi/
Author: Alain Jungo
Author-email: alain.jungo@artorg.unibe.ch
License: Apache 2.0
Keywords: medical image analysis,Image segmentation,Sampling image segmentations
Platform: UNKNOWN
Classifier: Development Status :: 3 - Alpha
Classifier: Intended Audience :: Developers
Classifier: Intended Audience :: Science/Research
Classifier: License :: OSI Approved :: Apache Software License
Classifier: Natural Language :: English
Classifier: Programming Language :: Python :: 3.6
Classifier: Topic :: Scientific/Engineering :: Mathematics
Classifier: Topic :: Scientific/Engineering :: Medical Science Apps.
Classifier: Topic :: Software Development :: Libraries :: Python Modules
Classifier: Topic :: Software Development :: Libraries
Requires-Python: >=3.6
Requires-Dist: Pillow (>=7.1.2)
Requires-Dist: numpy (>=1.18.5)
Requires-Dist: scipy (>=1.4.1)
